README.md
setup.py
dync/__init__.py
dync/auth.py
dync/client.py
dync/daemon.py
dync/exceptions.py
dync/messages.py
dync/server.py
dync/storage.py
dync.egg-info/PKG-INFO
dync.egg-info/SOURCES.txt
dync.egg-info/dependency_links.txt
dync.egg-info/entry_points.txt
dync.egg-info/requires.txt
dync.egg-info/top_level.txt