Metadata-Version: 1.0
Name: dync
Version: 1.0
Summary: A tcp-based client for data transfer.
Home-page: https://github.com/qbicsoftware/dync
Author: Sven Fillinger
Author-email: adrian.seyboldt@gmail.com
License: GPL2+
Platform: UNKNOWN
